{
  "파일명": "48420_2024_11_18_193800.jpg",
  "제목": "2024년 제1회 스타트업 창업박람회",
  "설명": "2024. 12. 20.(금) 10:00~17:00 노원구청 대강당(2층) 스타트업 IR 데모데이 개최 일시 | 2024. 12. 20.(금) 10:00~17:00 모집기간 | 2024. 11. 1.(수) ~ 11. 22.(금) 17:00 모집대상 | 노원구 내 창업 기업, 기계·소재, 전기·전자, 화학·공예, 바이오 등 5종 선발 보유 창업기업 10개사 내외 시상규모 | 총 400만원 내외 문의 | 인덕대학교 02. 950. 7374 이메일 | suuwls@induk.ac.kr",
  "카테고리": "진로",
  "세부카테고리": [
    "스타트업",
    "창업",
    "IR",
    "데모데이",
    "투자",
    "경진대회",
    "전시"
  ],
  "대상": {
    "연령": "전국민",
    "지역": "서울",
    "특이조건": []
  },
  "기간": {
    "start": "2024-11-01",
    "end": "2024-11-22"
  },
  "주최기관": [
    "노원구",
    "인덕대학교"
  ]
}