{
  "파일명": "49755_2025_04_03_135756.jpg",
  "제목": "푸드 트레일러 청년 창업자 모집",
  "설명": "모집기간 3. 24(월) ~ 4. 22(화) 13시까지 모집대상 19세~39세 청년 예비 창업자 또는 F&B 분야 청년 예비 재창업자 모집인원 1인(예비합격자 모집인원 2배수 선발) 모집분야 F&B&BA업(식·음료, 밀키트 등) 사업기간 2025년 6월~12월(기간에 따라 사업기간 조정 가능) 지원내용 영업공간 제공 및 장비대여 푸드트레일러, 빌트인 냉장고 등 대여(장비 및 자재 지원) 운영에 사용 될 집기류, 가스 등 개인 구매 창업지원 맞춤형 컨설팅(메뉴개발 등) 강북청년센터 연계지원 등록 필수사항 강북스마트팜센터 자율활동공간(1층, 연계형) SNS채널 및 운영을 통한 트레일러 홍보 적응을 위한 교육 제공 시범 운영 참여 남부 신청방법 강북청년센터 홈페이지 내 공지사항 [신청양식 다운로드] 이메일 접수(gb.man2@gmail.com)",
  "카테고리": "진로",
  "세부카테고리": [
    "청년",
    "창업",
    "푸드트레일러",
    "모집",
    "지원",
    "컨설팅",
    "사업"
  ],
  "대상": {
    "연령": "청년",
    "지역": "서울",
    "특이조건": []
  },
  "기간": {
    "start": "2025-03-24",
    "end": "2025-04-22"
  },
  "주최기관": [
    "강북청년센터",
    "마루",
    "광운대학교",
    "산학협력단",
    "키가강성"
  ]
}