{
  "파일명": "49516_2025_02_27_102523.jpg",
  "제목": "광운학습모임 모집",
  "설명": "학습전략개발(학습방법, 수업전후활동, 시험전략 등), 전공학습방법(학과 전공역량, 전공체계, 과목목록 등), 교과 관련 자유주제(교과목, 여학, 자격증, 시험대비 등) 학습 관련 자유 주제 학습리더를 주축으로 학습모임을 운영하고 관리하는 학습활동을 지원\n\n팀구성: 학습리더 1인과 구성원 3인 이상으로 총 4인 이상 구성\n학습리더 및 구성원 전공 제한 없이 구성 가능\n\n지원내용: 리더지원 300,000원 지급(2회 나누어 지급), 참빛포인트 10점\n우수팀 선정 시 문화상품권 200,000원 이상\n주간보고서 8회, 중간보고서 1회, 최종보고서 1회, 영상 1건 제출(총학습시간 16시간 이상)",
  "카테고리": "진로",
  "세부카테고리": [
    "학습전략",
    "전공학습",
    "팀구성",
    "지원내용",
    "문화상품권",
    "보고서",
    "영상"
  ],
  "대상": {
    "연령": "청소년",
    "지역": "전국",
    "특이조건": []
  },
  "기간": {
    "start": "2025-02-27",
    "end": "2025-03-16"
  },
  "주최기관": [
    "광운대학교",
    "교수학습센터"
  ]
}